aext_core/__init__.py
aext_core-0.0.1.dist-info/METADATA
aext_core-0.0.1.dist-info/WHEEL
aext_core-0.0.1.dist-info/RECORD
