Metadata-Version: 2.1
Name: aext-core
Version: 0.0.1
Summary: The aext-core component of anaconda-toolbox
License-Expression: BSD-3-Clause
